mltrack/__init__.py
mltrack/api.py
mltrack/cli.py
mltrack/config.py
mltrack/core.py
mltrack/data_store.py
mltrack/data_store_v2.py
mltrack/detectors.py
mltrack/git_utils.py
mltrack/introspection.py
mltrack/lineage.py
mltrack/llm.py
mltrack/model_registry.py
mltrack/pricing.py
mltrack/ui.py
mltrack/user_info.py
mltrack/utils.py
mltrack/version.py
mltrack/data/__init__.py
mltrack/data/litellm_snapshot.json
mltrack/deploy/__init__.py
mltrack/deploy/lambda_deploy.py
mltrack/deploy/modal_deploy.py
mltrack/deploy/s3_storage.py
mltrack/deployment/__init__.py
mltrack/deployment/cli_shortcuts.py
mltrack/deployment/api/__init__.py
mltrack/deployment/api/fastapi_generator.py
mltrack/deployment/docker/__init__.py
mltrack/deployment/docker/base_images.py
mltrack/deployment/docker/uv_builder.py
mltrack/templates/__init__.py
mltrack/templates/model_loader.py
mltrack_py-0.2.0.dist-info/METADATA
mltrack_py-0.2.0.dist-info/WHEEL
mltrack_py-0.2.0.dist-info/entry_points.txt
mltrack_py-0.2.0.dist-info/licenses/LICENSE
mltrack_py-0.2.0.dist-info/RECORD
