Metadata-Version: 2.4
Name: mltrack-py
Version: 0.2.0
Summary: Universal ML tracking tool for teams
Project-URL: Homepage, https://github.com/EconoBen/mltrack
Project-URL: Bug Reports, https://github.com/EconoBen/mltrack/issues
Project-URL: Source, https://github.com/EconoBen/mltrack
Author-email: Ben Labaschin <ben@labaschin.com>
License-Expression: MIT
License-File: LICENSE
Classifier: Development Status :: 4 - Beta
Classifier: Intended Audience :: Developers
Classifier: License :: OSI Approved :: MIT License
Classifier: Programming Language :: Python :: 3
Classifier: Programming Language :: Python :: 3.8
Classifier: Programming Language :: Python :: 3.9
Classifier: Programming Language :: Python :: 3.10
Classifier: Programming Language :: Python :: 3.11
Classifier: Programming Language :: Python :: 3.12
Classifier: Topic :: Scientific/Engineering :: Artificial Intelligence
Requires-Python: >=3.8
Requires-Dist: anthropic>=0.57.1
Requires-Dist: boto3>=1.37.38
Requires-Dist: click>=8.0
Requires-Dist: cloudpickle>=3.0.0
Requires-Dist: docker>=6.1.0
Requires-Dist: fastapi>=0.104.0
Requires-Dist: gitpython>=3.1
Requires-Dist: joblib>=1.3.0
Requires-Dist: mlflow>=2.0.0
Requires-Dist: openai>=1.93.2
Requires-Dist: psutil>=5.9
Requires-Dist: pydantic>=2.0
Requires-Dist: python-dotenv>=1.0.1
Requires-Dist: python-multipart>=0.0.6
Requires-Dist: pyyaml>=6.0
Requires-Dist: requests>=2.31.0
Requires-Dist: rich>=13.0
Requires-Dist: scikit-learn>=1.3.2
Requires-Dist: torch>=2.5.1
Requires-Dist: torchaudio>=2.5.1
Requires-Dist: torchvision>=0.20.1
Requires-Dist: tqdm>=4.67.1
Requires-Dist: uvicorn[standard]>=0.24.0
Provides-Extra: all
Requires-Dist: mltrack[s3,sklearn,tensorflow,torch]; extra == 'all'
Provides-Extra: dev
Requires-Dist: black>=23.0; extra == 'dev'
Requires-Dist: mypy>=1.0; extra == 'dev'
Requires-Dist: pre-commit>=3.0; extra == 'dev'
Requires-Dist: pytest-cov>=4.0; extra == 'dev'
Requires-Dist: pytest-mock>=3.0; extra == 'dev'
Requires-Dist: pytest>=7.0; extra == 'dev'
Requires-Dist: ruff>=0.1.0; extra == 'dev'
Provides-Extra: s3
Requires-Dist: boto3>=1.28.0; extra == 's3'
Provides-Extra: sklearn
Requires-Dist: scikit-learn>=1.0; extra == 'sklearn'
Provides-Extra: tensorflow
Requires-Dist: tensorflow>=2.0; extra == 'tensorflow'
Provides-Extra: torch
Requires-Dist: torch>=2.0; extra == 'torch'
